forgework/__init__.py
forgework/cli.py
forgework/debug.py
forge_work-1.1.0.dist-info/LICENSE
forge_work-1.1.0.dist-info/METADATA
forge_work-1.1.0.dist-info/WHEEL
forge_work-1.1.0.dist-info/entry_points.txt
forge_work-1.1.0.dist-info/RECORD
